batoid-0.8.0.dist-info/RECORD
batoid-0.8.0.dist-info/LICENSE
batoid-0.8.0.dist-info/WHEEL
batoid-0.8.0.dist-info/top_level.txt
batoid-0.8.0.dist-info/METADATA
batoid/trace.py
batoid/analysis.py
batoid/_version.py
batoid/coating.py
batoid/constants.py
batoid/medium.py
batoid/__init__.py
batoid/coordSys.py
batoid/rayVector.py
batoid/_batoid.cpython-39-darwin.so
batoid/obscuration.py
batoid/.gitignore
batoid/utils.py
batoid/lattice.py
batoid/app.py
batoid/optic.py
batoid/parse.py
batoid/plotUtils.py
batoid/surface.py
batoid/global_vars.py
batoid/coordTransform.py
batoid/.dylibs/libomp.dylib
batoid/data/SDSS/SDSS.yaml
batoid/data/misc/download_constellations.py
batoid/data/misc/download_bsc5.py
batoid/data/misc/constellations.fits
batoid/data/misc/BSC5.fits
batoid/data/LSST/ComCam_g.yaml
batoid/data/LSST/Rubin_v3.14_r.yaml
batoid/data/LSST/ComCamSpiders_z.yaml
batoid/data/LSST/ComCam_r.yaml
batoid/data/LSST/Rubin_v3.14_g.yaml
batoid/data/LSST/Rubin_v3.12_u.yaml
batoid/data/LSST/LSST_z.yaml
batoid/data/LSST/Rubin_v3.12_y.yaml
batoid/data/LSST/LSST_r_noobsc.yaml
batoid/data/LSST/LSST_r_baffles.yaml
batoid/data/LSST/Rubin_v3.12_g.yaml
batoid/data/LSST/ComCamSpiders_i.yaml
batoid/data/LSST/Rubin_v3.12_r.yaml
batoid/data/LSST/ComCam_y.yaml
batoid/data/LSST/Rubin_v3.14_y.yaml
batoid/data/LSST/LSST_i.yaml
batoid/data/LSST/ComCam_u.yaml
batoid/data/LSST/Rubin_v3.14_u.yaml
batoid/data/LSST/ComCamSpiders_g.yaml
batoid/data/LSST/ComCam_z.yaml
batoid/data/LSST/Rubin_v3.14_z.yaml
batoid/data/LSST/ComCamSpiders_r.yaml
batoid/data/LSST/Rubin_v3.12_i.yaml
batoid/data/LSST/LSST_g.yaml
batoid/data/LSST/CBP.yaml
batoid/data/LSST/LSST_r.yaml
batoid/data/LSST/LSST_y.yaml
batoid/data/LSST/Rubin_v3.12_z.yaml
batoid/data/LSST/Rubin_v3.14_i.yaml
batoid/data/LSST/ComCam_i.yaml
batoid/data/LSST/LSST_u.yaml
batoid/data/LSST/ComCamSpiders_y.yaml
batoid/data/LSST/LSST_g_500.yaml
batoid/data/LSST/ComCamSpiders_u.yaml
batoid/data/LSST/LSST_r_align_holes.yaml
batoid/data/DECam/DECam.yaml
batoid/data/HSC/HSC_old.yaml
batoid/data/HSC/HSC_no_obsc.yaml
batoid/data/HSC/HSC.yaml
