Metadata-Version: 2.2
Name: batoid
Version: 0.8.0
Summary: Optics raytracer
Home-page: https://github.com/jmeyers314/batoid
Author: Josh Meyers
Author-email: jmeyers314@gmail.com
Project-URL: Documentation, https://jmeyers314.github.io/batoid/overview.html
Project-URL: Source, https://github.com/jmeyers314/batoid
Project-URL: Tracker, https://github.com/jmeyers314/batoid/issues
Classifier: Development Status :: 3 - Alpha
Classifier: Intended Audience :: Science/Research
Classifier: License :: OSI Approved :: BSD License
Classifier: Programming Language :: C++
Classifier: Programming Language :: Python :: 3
Classifier: Topic :: Scientific/Engineering :: Astronomy
Classifier: Topic :: Scientific/Engineering :: Physics
Requires-Python: >=3.9
License-File: LICENSE
Requires-Dist: pybind11
Requires-Dist: numpy
Requires-Dist: pyyaml
Requires-Dist: scipy
Requires-Dist: galsim
Requires-Dist: matplotlib
Requires-Dist: astropy
Dynamic: author
Dynamic: author-email
Dynamic: classifier
Dynamic: description
Dynamic: description-content-type
Dynamic: home-page
Dynamic: project-url
Dynamic: requires-dist
Dynamic: requires-python
Dynamic: summary
